scraper/__init__.py
scraper/scraper.py
scraper_Rafihatu-0.0.3.dist-info/LICENSE
scraper_Rafihatu-0.0.3.dist-info/METADATA
scraper_Rafihatu-0.0.3.dist-info/WHEEL
scraper_Rafihatu-0.0.3.dist-info/top_level.txt
scraper_Rafihatu-0.0.3.dist-info/RECORD
