Metadata-Version: 2.1
Name: scraper-Rafihatu
Version: 0.0.3
Summary: A small eBay web scraper package
Home-page: https://github.com/Rafiatu/eBay-scraper
Author: Rafihatu Bello
Author-email: rafibella101@gmail.com
License: UNKNOWN
Project-URL: Bug Tracker, https://github.com/Rafiatu/eBay-scraper/issues
Platform: UNKNOWN
Classifier: Programming Language :: Python :: 3
Classifier: License :: OSI Approved :: MIT License
Classifier: Operating System :: OS Independent
Requires-Python: >=3.6
License-File: LICENSE
